mdreftidy/__init__.py
mdreftidy/cli.py
mdreftidy/mdreftidy.py
mdreftidy-0.6.1.dist-info/LICENSE.md
mdreftidy-0.6.1.dist-info/METADATA
mdreftidy-0.6.1.dist-info/WHEEL
mdreftidy-0.6.1.dist-info/entry_points.txt
mdreftidy-0.6.1.dist-info/top_level.txt
mdreftidy-0.6.1.dist-info/RECORD
