Metadata-Version: 2.1
Name: mdreftidy
Version: 0.6.1
Summary: CLI to tidy ({renumber,move-to-bottom,sort,clean}) up {image,link} references for markdown.
Author-email: AYF <realazthat@gmail.com>
License: MIT License
Project-URL: Homepage, https://github.com/realazthat/mdreftidy
Project-URL: Documentation, https://github.com/realazthat/mdreftidy
Project-URL: Repository, https://github.com/realazthat/mdreftidy
Keywords: github,markdown,readme,documentation,preprocessor,documentation-tool,readme-md
Classifier: Operating System :: OS Independent
Classifier: Programming Language :: Python :: 3.8
Classifier: Programming Language :: Python :: 3.9
Classifier: Programming Language :: Python :: 3.10
Classifier: Programming Language :: Python :: 3.11
Classifier: Programming Language :: Python :: 3.12
Requires-Python: >=3.8
License-File: LICENSE.md
Requires-Dist: colorama<1,>=0.4
Requires-Dist: mistletoe<2,>=1
Requires-Dist: pyyaml<7,>=6
Requires-Dist: rich<14,>=13
Requires-Dist: rich-argparse<2,>=1
Requires-Dist: types-colorama<1,>=0.4
Requires-Dist: typing-extensions<5,>=4
Requires-Dist: importlib-metadata; python_version < "3.8"
Provides-Extra: dev
Requires-Dist: argcomplete==3.3.0; extra == "dev"
Requires-Dist: autoflake==2.3.1; extra == "dev"
Requires-Dist: backports-tarfile==1.1.1; extra == "dev"
Requires-Dist: beautifulsoup4==4.12.3; extra == "dev"
Requires-Dist: bs4==0.0.2; extra == "dev"
Requires-Dist: certifi==2024.2.2; extra == "dev"
Requires-Dist: cffi==1.16.0; extra == "dev"
Requires-Dist: cfgv==3.4.0; extra == "dev"
Requires-Dist: changeguard==0.3.1; extra == "dev"
Requires-Dist: charset-normalizer==3.3.2; extra == "dev"
Requires-Dist: colorama==0.4.6; extra == "dev"
Requires-Dist: cryptography==42.0.5; extra == "dev"
Requires-Dist: defusedxml==0.7.1; extra == "dev"
Requires-Dist: distlib==0.3.8; extra == "dev"
Requires-Dist: docutils==0.20.1; extra == "dev"
Requires-Dist: filelock==3.14.0; extra == "dev"
Requires-Dist: identify==2.5.36; extra == "dev"
Requires-Dist: idna==3.7; extra == "dev"
Requires-Dist: importlib-metadata==7.1.0; extra == "dev"
Requires-Dist: importlib-resources==6.4.0; extra == "dev"
Requires-Dist: isort==5.13.2; extra == "dev"
Requires-Dist: jaraco-classes==3.4.0; extra == "dev"
Requires-Dist: jaraco-context==5.3.0; extra == "dev"
Requires-Dist: jaraco-functools==4.0.1; extra == "dev"
Requires-Dist: jeepney==0.8.0; extra == "dev"
Requires-Dist: jinja2==3.1.3; extra == "dev"
Requires-Dist: keyring==25.2.0; extra == "dev"
Requires-Dist: markdown-it-py==3.0.0; extra == "dev"
Requires-Dist: markupsafe==2.1.5; extra == "dev"
Requires-Dist: mdremotifier==0.3.1; extra == "dev"
Requires-Dist: mdurl==0.1.2; extra == "dev"
Requires-Dist: mistletoe==1.3.0; extra == "dev"
Requires-Dist: more-itertools==10.2.0; extra == "dev"
Requires-Dist: mypy==1.8.0; extra == "dev"
Requires-Dist: mypy-extensions==1.0.0; extra == "dev"
Requires-Dist: nh3==0.2.17; extra == "dev"
Requires-Dist: nodeenv==1.8.0; extra == "dev"
Requires-Dist: pathspec==0.12.1; extra == "dev"
Requires-Dist: pexpect==4.9.0; extra == "dev"
Requires-Dist: pkginfo==1.10.0; extra == "dev"
Requires-Dist: platformdirs==4.2.1; extra == "dev"
Requires-Dist: pre-commit==3.5.0; extra == "dev"
Requires-Dist: ptyprocess==0.7.0; extra == "dev"
Requires-Dist: pycparser==2.22; extra == "dev"
Requires-Dist: pyflakes==3.2.0; extra == "dev"
Requires-Dist: pygments==2.17.2; extra == "dev"
Requires-Dist: pyright==1.1.352; extra == "dev"
Requires-Dist: pyyaml==6.0.1; extra == "dev"
Requires-Dist: readme-renderer==43.0; extra == "dev"
Requires-Dist: requests==2.31.0; extra == "dev"
Requires-Dist: requests-toolbelt==1.0.0; extra == "dev"
Requires-Dist: rfc3986==2.0.0; extra == "dev"
Requires-Dist: rich==13.7.1; extra == "dev"
Requires-Dist: rich-argparse==1.4.0; extra == "dev"
Requires-Dist: secretstorage==3.3.3; extra == "dev"
Requires-Dist: semver==3.0.2; extra == "dev"
Requires-Dist: snipinator==3.1.1; extra == "dev"
Requires-Dist: soupsieve==2.5; extra == "dev"
Requires-Dist: toml-sort==0.23.1; extra == "dev"
Requires-Dist: tomli==2.0.1; extra == "dev"
Requires-Dist: tomlkit==0.12.4; extra == "dev"
Requires-Dist: twine==5.0.0; extra == "dev"
Requires-Dist: types-beautifulsoup4==4.12.0.20240504; extra == "dev"
Requires-Dist: types-colorama==0.4.15.20240311; extra == "dev"
Requires-Dist: types-html5lib==1.1.11.20240228; extra == "dev"
Requires-Dist: types-pyyaml==6.0.12.20240311; extra == "dev"
Requires-Dist: typing-extensions==4.10.0; extra == "dev"
Requires-Dist: urllib3==2.2.1; extra == "dev"
Requires-Dist: virtualenv==20.26.0; extra == "dev"
Requires-Dist: xmltodict==0.13.0; extra == "dev"
Requires-Dist: yapf==0.40.2; extra == "dev"
Requires-Dist: yq==3.2.3; extra == "dev"
Requires-Dist: zipp==3.18.1; extra == "dev"
Provides-Extra: prod
Requires-Dist: colorama==0.4.6; extra == "prod"
Requires-Dist: markdown-it-py==3.0.0; extra == "prod"
Requires-Dist: mdurl==0.1.2; extra == "prod"
Requires-Dist: mistletoe==1.3.0; extra == "prod"
Requires-Dist: pygments==2.17.2; extra == "prod"
Requires-Dist: rich==13.7.1; extra == "prod"
Requires-Dist: rich-argparse==1.4.0; extra == "prod"
Requires-Dist: types-colorama==0.4.15.20240311; extra == "prod"
Requires-Dist: typing-extensions==4.11.0; extra == "prod"
Requires-Dist: pyyaml==6.0.1; extra == "prod"
